darwin_handlers/__init__.py
darwin_handlers/config/README.md
darwin_handlers/config/__init__.py
darwin_handlers/config/backtest/__init__.py
darwin_handlers/config/backtest/core.py
darwin_handlers/config/configuration.py
darwin_handlers/config/fields.py
darwin_handlers/config/general/__init__.py
darwin_handlers/config/general/assets.py
darwin_handlers/config/general/portfolio.py
darwin_handlers/config/general/strategy.py
darwin_handlers/config/general/time.py
darwin_handlers/config/general/users.py
darwin_handlers/config/reinforcement/__init__.py
darwin_handlers/config/reinforcement/core.py
darwin_handlers/core/__init__.py
darwin_handlers/core/accessor.py
darwin_handlers/core/creation.py
darwin_handlers/data/__init__.py
darwin_handlers/data/stochastic_generator.py
darwin_handlers/environments/__init__.py
darwin_handlers/environments/backtest.py
darwin_handlers/environments/reinforcement.py
darwin_handlers/handlers/__init__.py
darwin_handlers/handlers/abstracts/__init__.py
darwin_handlers/handlers/abstracts/strategy.py
darwin_handlers/handlers/allocation.py
darwin_handlers/handlers/exchange.py
darwin_handlers/handlers/files/__init__.py
darwin_handlers/handlers/files/models/README.md
darwin_handlers/handlers/files/models/README.pdf
darwin_handlers/handlers/files/models/__init__.py
darwin_handlers/handlers/files/strategy.md
darwin_handlers/handlers/ordering/__init__.py
darwin_handlers/handlers/ordering/broker.py
darwin_handlers/handlers/ordering/order.py
darwin_handlers/handlers/requirements.py
darwin_handlers/handlers/statespace.py
darwin_handlers/handlers/strategy/__init__.py
darwin_handlers/handlers/strategy/core.py
darwin_handlers/handlers/trades.py
darwin_handlers/handlers/user.py
darwin_handlers/search/__init__.py
darwin_handlers/search/backtesting/accessors/__init__.py
darwin_handlers/search/backtesting/accessors/create.py
darwin_handlers/search/backtesting/accessors/info.py
darwin_handlers/search/backtesting/accessors/remove.py
darwin_handlers-0.1.2.dist-info/WHEEL
darwin_handlers-0.1.2.dist-info/METADATA
darwin_handlers-0.1.2.dist-info/RECORD
