Metadata-Version: 2.1
Name: darwin-handlers
Version: 0.1.2
Summary: 
Author: Kevin Hill
Author-email: kivo360@gmail.com
Requires-Python: >=3.6.0
Classifier: Programming Language :: Python :: 3
Classifier: Programming Language :: Python :: 3.6
Classifier: Programming Language :: Python :: 3.7
Classifier: Programming Language :: Python :: 3.8
Requires-Dist: dask (>=2.14.0,<3.0.0)
Requires-Dist: faker (>=4.0.3,<5.0.0)
Requires-Dist: jamboree (==0.7.2)
Requires-Dist: matplotlib (>=3.2.1,<4.0.0)
Requires-Dist: maya (>=0.6.1,<0.7.0)
Requires-Dist: pandas_datareader (>=0.8.1,<0.9.0)
Requires-Dist: skorch (>=0.8.0,<0.9.0)
